webdomains/__init__.py
webdomains/cli.py
webdomains/core.py
webdomains/utils.py
webdomains/templates/server.conf
webdomains-1.0.0b3.dist-info/METADATA
webdomains-1.0.0b3.dist-info/WHEEL
webdomains-1.0.0b3.dist-info/entry_points.txt
webdomains-1.0.0b3.dist-info/licenses/LICENSE
webdomains-1.0.0b3.dist-info/RECORD
