Metadata-Version: 2.3
Name: webdomains
Version: 1.0.0b3
Summary: Manage your Web domains served by NGINX
Project-URL: Repository, https://framagit.org/cliss21/webdomains
Project-URL: Issues, https://framagit.org/cliss21/webdomains/-/issues
Author-email: Cliss XXI <contact@cliss21.com>
License-Expression: GPL-3.0-or-later
License-File: LICENSE
Classifier: Development Status :: 4 - Beta
Classifier: License :: OSI Approved :: GNU General Public License v3 (GPLv3)
Classifier: Operating System :: POSIX :: Linux
Classifier: Programming Language :: Python :: 3 :: Only
Classifier: Programming Language :: Python :: 3.8
Classifier: Programming Language :: Python :: 3.9
Classifier: Programming Language :: Python :: 3.10
Classifier: Programming Language :: Python :: 3.11
Classifier: Programming Language :: Python :: 3.12
Classifier: Topic :: Internet :: WWW/HTTP :: HTTP Servers
Requires-Python: >=3.8
Requires-Dist: click>=7.0
Requires-Dist: jinja2>=2.10
Provides-Extra: dev
Requires-Dist: pytest; extra == 'dev'
Requires-Dist: pytest-cov; extra == 'dev'
Requires-Dist: ruff~=0.3.5; extra == 'dev'
